README.md
setup.py
microsoftbotframework/__init__.py
microsoftbotframework/activity.py
microsoftbotframework/cache.py
microsoftbotframework/config.py
microsoftbotframework/conversationoperations.py
microsoftbotframework/msbot.py
microsoftbotframework/response.py
microsoftbotframework/runcelery.py
microsoftbotframework/state.py
microsoftbotframework.egg-info/PKG-INFO
microsoftbotframework.egg-info/SOURCES.txt
microsoftbotframework.egg-info/dependency_links.txt
microsoftbotframework.egg-info/not-zip-safe
microsoftbotframework.egg-info/requires.txt
microsoftbotframework.egg-info/top_level.txt