Metadata-Version: 2.1
Name: microsoftbotframework
Version: 0.3.3
Summary: A wrapper for the microsoft bot framework API
Home-page: https://github.com/Grungnie/microsoftbotframework
Author: Matthew Brown
Author-email: mbrown1508@outlook.com
License: MIT
Keywords: microsoft bot framework flask celery
Platform: UNKNOWN
Classifier: Development Status :: 3 - Alpha
Classifier: License :: OSI Approved :: MIT License
Classifier: Programming Language :: Python :: 3.6
Classifier: Topic :: Communications :: Chat
Provides-Extra: test
